morpho/__init__.py
morpho/brillouinzone.py
morpho/exceptions.py
morpho/geometry.py
morpho/solver.py
morpho/utils.py
morpho.py-0.0.4.dist-info/LICENSE
morpho.py-0.0.4.dist-info/WHEEL
morpho.py-0.0.4.dist-info/METADATA
morpho.py-0.0.4.dist-info/RECORD
