Metadata-Version: 2.1
Name: morpho.py
Version: 0.0.4
Summary: 
License: MIT
Author: Tiago Vilela
Author-email: tiagovla@gmail.com
Requires-Python: >=3.8,<4.0
Classifier: License :: OSI Approved :: MIT License
Classifier: Programming Language :: Python :: 3
Classifier: Programming Language :: Python :: 3.8
Classifier: Programming Language :: Python :: 3.9
Requires-Dist: matplotlib (>=3.3.4,<4.0.0)
Requires-Dist: numpy (>=1.20.1,<2.0.0)
Requires-Dist: scipy (>=1.6.1,<2.0.0)
